{
  "id": "persian-tea-road",
  "name": "波斯茶路",
  "nameEn": "The Persian Tea Road",
  "continent": "亚洲",
  "country": "伊朗/中国/中亚",
  "subtitle": "从长安到伊斯法罕——丝绸之路上的波斯茶香",
  "summary": "波斯（伊朗）是丝绸之路上的茶叶贸易重镇，茶文化在波斯已有数百年历史。茶叶通过丝绸之路从中国传入波斯，最早可追溯至唐代。波斯商人将中国砖茶和绿茶运至波斯，逐渐形成了独特的波斯茶文化——用萨玛瓦尔（Samovar，俄式茶炊）煮茶，以透明玻璃杯饮用，搭配藏红花冰糖（Nabat）和波斯甜点。15-16世纪，波斯茶馆（Chaikhaneh）成为波斯社会文化生活的中心。波斯茶路从中国西安出发，经中亚穿越伊朗高原，连接德黑兰、伊斯法罕、设拉子等历史名城，最终抵达大不里士和伊斯坦布尔。",
  "difficulty": "中高——穿越伊朗高原和沙漠，路途遥远但历史文化底蕴深厚",
  "mainTea": "伊朗拉希詹红茶、吉兰红茶、伊朗藏红花茶、伊朗玫瑰茶",
  "distance": "约2500公里（从德黑兰至大不里士，含主要茶区）",
  "duration": "古代商队约3-4个月，现代自驾约7-10天",
  "bestSeason": "3-5月和9-11月（伊朗高原气候温和，避开夏季酷热和冬季严寒）",
  "terrain": "伊朗高原—里海沿岸—厄尔布尔士山脉—卡维尔盐漠—扎格罗斯山脉",
  "detailRoute": "起点：德黑兰（Tehran，波斯茶都，大巴扎茶叶市场）→ 拉希詹（Lahijan，伊朗茶都，里海茶区）→ 拉什特（Rasht，吉兰省首府）→ 加兹温（Qazvin，萨法维古都）→ 伊斯法罕（Isfahan，波斯茶文化之都，伊玛目广场茶馆）→ 设拉子（Shiraz，哈菲兹墓旁茶馆）→ 亚兹德（Yazd，沙漠古城茶馆）→ 大不里士（Tabriz，终点，连接伊斯坦布尔茶路，大巴扎世界遗产）。",
  "stations": [
    {
      "distKm": 0,
      "alt": 1200,
      "name": "德黑兰",
      "coord": [
        35.69,
        51.39
      ],
      "distance": "0km",
      "altitude": "1200m",
      "road": "大都市",
      "desc": "起点，波斯茶文化中心，大巴扎茶叶市场千年传承。德黑兰大巴扎（Grand Bazaar）是伊朗最大的传统市场——茶叶区（Bazaar-e Chai）的店铺鳞次栉比，空气中弥漫着红茶、藏红花和玫瑰的香气。德黑兰人每天从早到晚都在喝茶——街头茶馆遍布每个角落"
    },
    {
      "distKm": 320,
      "alt": 0,
      "name": "拉希詹",
      "coord": [
        37.21,
        50.00
      ],
      "distance": "320km",
      "altitude": "0m",
      "road": "里海沿岸公路",
      "desc": "伊朗茶都，里海沿岸茶区，1900年伊朗茶产业诞生地。拉希詹位于厄尔布尔士山脉北麓、里海之滨——湿润的海洋气候和肥沃的土壤使其成为伊朗最优质的茶叶产区。拉希詹茶博物馆展示了伊朗茶产业从无到有的百年历程"
    },
    {
      "distKm": 350,
      "alt": 0,
      "name": "拉什特",
      "coord": [
        37.28,
        49.59
      ],
      "distance": "350km",
      "altitude": "0m",
      "road": "里海沿岸公路",
      "desc": "吉兰省茶叶中心，伊朗最大茶区，茶园沿里海延绵。吉兰省是伊朗茶产业的摇篮——全省茶园面积超过25000公顷，产量占伊朗茶叶总产量的90%以上。拉什特的茶市每周举办茶叶拍卖会，伊朗各地的茶商汇聚于此"
    },
    {
      "distKm": 500,
      "alt": 1300,
      "name": "加兹温",
      "coord": [
        36.27,
        50.00
      ],
      "distance": "500km",
      "altitude": "1300m",
      "road": "萨法维古道",
      "desc": "萨法维王朝（1501-1736）古都，丝绸之路上的重要驿站。加兹温是萨法维王朝的第二首都——16世纪波斯宫廷在此设立了专门的\u201c茶房\u201d，负责为皇室和外国使节备茶。加兹温的传统茶馆保留了萨法维时期的建筑风格和茶道仪式"
    },
    {
      "distKm": 900,
      "alt": 1600,
      "name": "伊斯法罕",
      "coord": [
        32.65,
        51.67
      ],
      "distance": "900km",
      "altitude": "1600m",
      "road": "皇家大道",
      "desc": "\u201c半天下之城\u201d——16世纪波斯谚语\u201c伊斯法罕，半天下\u201d（Esfahān nesf-e jahān），波斯茶文化之都。伊玛目广场（Naghsh-e Jahan）是仅次于天安门广场的世界第二大广场——广场周围数以百计的茶馆和咖啡馆将波斯茶文化展现得淋漓尽致。伊斯法罕的茶馆以藏红花茶和玫瑰茶最为著名"
    },
    {
      "distKm": 1400,
      "alt": 1500,
      "name": "设拉子",
      "coord": [
        29.61,
        52.54
      ],
      "distance": "1400km",
      "altitude": "1500m",
      "road": "波斯花园之路",
      "desc": "诗人之城，哈菲兹墓旁百年茶馆，以玫瑰茶和藏红花茶闻名。设拉子是波斯最伟大的诗人哈菲兹（1325-1389）的故乡——他的诗歌中多次提到茶和玫瑰。哈菲兹墓旁的茶馆是波斯文人雅士的聚会之地——人们在此品茶、读诗、谈论人生"
    },
    {
      "distKm": 1900,
      "alt": 1200,
      "name": "亚兹德",
      "coord": [
        31.90,
        54.37
      ],
      "distance": "1900km",
      "altitude": "1200m",
      "road": "沙漠商道",
      "desc": "沙漠古城，丝绸之路上的风塔茶馆，独特的地下茶室。亚兹德是世界上最古老的土坯城市之一——沙漠中的炎热气候使亚兹德人发明了\u201c风塔\u201d（Badgir，天然空调系统）。亚兹德的地下茶馆（建于地下数米）借用风塔降温——即使在炎热的夏季，茶馆内依然凉爽宜人"
    },
    {
      "distKm": 2500,
      "alt": 1400,
      "name": "大不里士",
      "coord": [
        38.08,
        46.29
      ],
      "distance": "2500km",
      "altitude": "1400m",
      "road": "丝绸之路古道",
      "desc": "终点，连接伊斯坦布尔，大巴扎为世界遗产，波斯茶路西端枢纽。大不里士大巴扎是丝绸之路西段最大的贸易市场——茶叶区是巴扎中最重要的区域之一。波斯的红茶和茶具从这里经土耳其进入欧洲——大不里士的茶馆是波斯茶路和土耳其茶文化交汇的见证"
    }
  ],
  "roadLegend": [
    {
      "type": "大都市",
      "color": "#B8860B"
    },
    {
      "type": "里海沿岸公路",
      "color": "#4169E1"
    },
    {
      "type": "萨法维古道",
      "color": "#CD853F"
    },
    {
      "type": "皇家大道",
      "color": "#FFD700"
    },
    {
      "type": "波斯花园之路",
      "color": "#228B22"
    },
    {
      "type": "沙漠商道",
      "color": "#D2B48C"
    },
    {
      "type": "丝绸之路古道",
      "color": "#8B4513"
    }
  ],
  "story": "<p><strong>唐代·茶叶传入波斯</strong>——茶叶最早通过丝绸之路传入波斯（今伊朗）的时间可追溯至唐代（7-9世纪）。波斯商人在长安和洛阳的市场上首次接触到中国茶叶——他们将砖茶和绿茶随驼队沿丝绸之路运回波斯。波斯人对这种来自东方的神奇饮品产生了浓厚的兴趣——波斯医学家伊本·西那（Ibn Sina，980-1037，即阿维森纳）在《医典》中记载了茶叶的药用价值，认为\u201c茶能清心明目、提神醒脑\u201d。这是西方医学文献中最早关于茶叶的记载之一。</p>\n    <p><strong>萨法维王朝·波斯茶馆的诞生</strong>——16世纪，萨法维王朝（1501-1736）将波斯茶文化推向了高峰。阿巴斯一世（Shah Abbas I，1587-1629在位）将首都迁至伊斯法罕，并在此修建了宏伟的伊玛目广场。广场周围的茶馆（Chaikhaneh）成为波斯社会文化生活的中心——商人、诗人、学者和普通市民在茶馆中品茶、谈天、抽水烟（Qalyan）。萨法维时期的波斯画家留下了大量描绘茶馆场景的细密画（Miniature）——画中人们围坐在地毯上，面前放着茶壶和玻璃杯，身后是繁花似锦的波斯花园。</p>\n    <p><strong>萨玛瓦尔·波斯茶文化的灵魂</strong>——萨玛瓦尔（Samovar）是波斯茶文化最具标志性的器物。这种源自俄罗斯的茶炊在19世纪传入波斯后，迅速成为波斯家庭和茶馆的必备之物。萨玛瓦尔用木炭或电加热——顶部的小茶壶里盛着浓茶，下面的大壶里是热水。饮用时，先将少量浓茶倒入透明玻璃杯中，再根据个人口味加入热水稀释——波斯人喜欢琥珀色的茶汤，不浓不淡。萨玛瓦尔不仅是煮茶工具，更是波斯家庭聚会和社交活动的中心——\u201c萨玛瓦尔的茶香，是波斯家庭的灵魂。\u201d</p>\n    <p><strong>藏红花冰糖·波斯茶的甜蜜伴侣</strong>——波斯人喝茶不加牛奶，但一定要配上藏红花冰糖（Nabat）。藏红花（Saffron）是波斯最珍贵的香料——每一克藏红花需要采摘数百朵藏红花的花蕊，因此被称为\u201c红色黄金\u201d。波斯人将藏红花浸泡在冰糖中，使其吸收了藏红花的金色和香气。喝茶时，将一小块藏红花冰糖含在口中，让茶水流过冰糖——甜味和藏红花的香气在口中慢慢释放，这是波斯茶最独特的品饮方式。除了藏红花冰糖，波斯人还会在茶中加入玫瑰花瓣、豆蔻、肉桂和薄荷——每一种香料都赋予了茶不同的风味层次。</p>\n    <p><strong>古列斯坦宫·波斯宫廷茶礼</strong>——德黑兰的古列斯坦宫（Golestan Palace，UNESCO世界遗产）是波斯宫廷茶礼的最佳见证。卡扎尔王朝（1789-1925）的国王们在此举行盛大的茶会——外国使节和贵族受邀参加。波斯宫廷茶礼有着严格的礼仪——茶必须由专门的\u201c茶侍\u201d（Chai-dar）用银质托盘端上，先敬国王，再按官阶依次献茶。茶会期间，乐师弹奏波斯传统乐器，诗人朗诵哈菲兹的诗歌，舞者表演波斯舞蹈——茶、诗、音乐、舞蹈在波斯宫廷中完美融合。古列斯坦宫的镜厅中仍然陈列着卡扎尔时期的银质萨玛瓦尔和描金茶具。</p>\n    <p><strong>波斯茶馆·社会的缩影</strong>——波斯茶馆（Chaikhaneh）是波斯社会最真实的缩影。在茶馆中，富商和乞丐可以同桌品茶，学者和文盲可以畅谈人生——茶打破了阶级的界限，成为波斯社会最平等的媒介。传统的波斯茶馆分为室外和室内两部分——室外是临街的露天茶座，铺着波斯地毯，放着矮桌和靠垫；室内是拱顶大厅，墙上挂着波斯细密画和镜子，中间是萨玛瓦尔。茶馆的茶单非常简单——只有红茶和绿茶，但茶点却琳琅满目：藏红花冰糖、波斯甜点（Gaz、Sohan、Baklava）、椰枣、无花果干和坚果。在伊斯法罕的茶馆中，你还经常可以听到波斯传统音乐和诗歌朗诵——\u201c茶、诗、音乐，是波斯人灵魂的三位一体。\u201d</p>\n    <p><strong>拉希詹·伊朗茶都</strong>——拉希詹是伊朗茶产业的心脏。1900年，伊朗企业家卡赛夫·萨尔塔内（Kashef al-Saltaneh）——时任伊朗驻印度领事——从印度秘密带回3000株茶苗和2000颗茶种，在拉希詹试种成功。萨尔塔内因此被称为\u201c伊朗茶之父\u201d——他的陵墓就建在拉希詹的茶园中，被伊朗茶人视为圣地。拉希詹的茶园沿着厄尔布尔士山脉北麓的缓坡延伸——里海湿润的空气和肥沃的土壤赋予了拉希詹红茶独特的香气和口感。拉希詹茶博物馆展示了伊朗茶产业从无到有的百年历程——从萨尔塔内带回的第一株茶苗，到如今吉兰省数万公顷的茶园，伊朗茶产业走过了一条不平凡的道路。</p>\n    <p><strong>伊斯法罕·半天下之城</strong>——伊斯法罕是波斯茶文化的巅峰之作。16世纪的波斯谚语\u201c伊斯法罕，半天下\u201d（Esfahān nesf-e jahān）——意思是伊斯法罕的美景和文化占据了天下的一半。伊玛目广场上的茶馆是波斯茶文化最集中的展示地——在世界上最美的广场上，坐在波斯地毯上，端着一杯琥珀色的波斯红茶，望着广场上夕阳下的蓝色清真寺，这是波斯茶文化最诗意的瞬间。伊斯法罕的茶馆以藏红花茶和玫瑰茶最为著名——藏红花茶呈金黄色，玫瑰茶呈淡粉色，盛在透明玻璃杯中，宛若液体宝石。伊斯法罕的茶馆老板会自豪地告诉你：\u201c在伊斯法罕，茶不是饮料，是一门艺术。\u201d</p>\n    <p><strong>设拉子·诗人的茶香</strong>——设拉子是波斯最伟大的诗人哈菲兹（1325-1389）的故乡。哈菲兹是波斯文学的巅峰——他的诗歌以爱情、美酒和自由为主题，被誉为\u201c波斯诗圣\u201d。哈菲兹墓旁的茶馆是设拉子最具文化气息的地方——人们在此品茶、读诗、占卜。波斯人有一种独特的习俗——用哈菲兹的诗集进行占卜（Fal-e Hafez）：在茶馆中翻开哈菲兹诗集，随机选一首诗，诗的意境被认为是对提问者命运的预言。设拉子的茶馆里常年飘荡着玫瑰茶和藏红花茶的香气——\u201c设拉子的茶，一半是茶香，一半是诗香。\u201d</p>\n    <p><strong>亚兹德·沙漠中的茶室</strong>——亚兹德是世界上最古老的土坯城市之一，也是沙漠中的绿洲。亚兹德的夏季气温高达40度以上——聪明的亚兹德人发明了\u201c风塔\u201d（Badgir），利用自然风给建筑降温。亚兹德的地下茶馆就建在风塔下方——茶馆深入地下数米，夏季温度比地面低10-15度。在炎热的沙漠中，坐在凉爽的地下茶馆里，喝一杯加了薄荷和玫瑰花瓣的波斯红茶——这是沙漠旅行者最奢侈的享受。亚兹德的茶馆还保留着古老的\u201c水烟\u201d（Qalyan）传统——当地人在品茶之余，会抽一壶水烟，烟雾缭绕中，诉说着丝绸之路上的千年往事。</p>\n    <p><strong>大不里士·波斯茶路的西端</strong>——大不里士是波斯茶路西端的终点。大不里士大巴扎是联合国教科文组织世界遗产——也是丝绸之路西段最大的传统市场。大巴扎中的茶叶区（Timcheh-e Chai）是波斯茶路最重要的贸易枢纽——来自中国、印度和锡兰的茶叶在此集散，经奥斯曼帝国进入欧洲。大不里士的茶馆是波斯茶文化和土耳其茶文化交汇的见证——在这里，你可以喝到波斯风格的藏红花茶，也可以喝到土耳其风格的浓红茶。大不里士的茶商们至今仍然用传统方式交易茶叶——在大巴扎的茶馆中，茶商和买家面对面坐下，边喝茶边讨价还价，一杯茶喝完，生意也就谈成了。</p>\n    <p><strong>波斯茶路·千年茶香未散</strong>——波斯茶路虽然在地理上跨越了从长安到伊斯法罕的数千公里，但它的文化精髓却浓缩在一杯琥珀色的波斯红茶之中。从唐代的驼队商旅，到萨法维的宫廷茶礼，到今天的德黑兰街头茶馆——波斯茶文化始终保持着独特的魅力。伊朗是世界上人均茶叶消费量最高的国家之一——每个伊朗人每年平均消费超过1.5公斤茶叶。在伊朗，茶不仅是饮料，更是社交的媒介、文化的象征和生活的仪式。当你坐在伊斯法罕伊玛目广场的茶馆中，端起一杯波斯红茶——那琥珀色的茶汤中，映照着从丝绸之路到今天的千年茶香。</p>",
  "teas": [
    "lahijan-tea",
    "fouman-tea",
    "gilani-chai",
    "langarud-tea",
    "gorgan-black",
    "shirvan-black",
    "tonkabon-green"
  ],
  "regions": [
    "德黑兰",
    "拉希詹",
    "拉什特",
    "加兹温",
    "伊斯法罕",
    "设拉子",
    "亚兹德",
    "大不里士"
  ],
  "imageIcon": "🕌",
  "color": "#8B4513",
  "tags": [
    "波斯",
    "丝绸之路",
    "萨玛瓦尔",
    "藏红花茶",
    "伊斯法罕",
    "茶馆",
    "千年传承",
    "设拉子"
  ]
}